rulelift/__init__.py
rulelift/analysis/__init__.py
rulelift/analysis/rule_analysis.py
rulelift/analysis/strategy_analysis.py
rulelift/analysis/variable_analysis.py
rulelift/data/feas_target.csv
rulelift/data/hit_rule_info.csv
rulelift/metrics/__init__.py
rulelift/metrics/advanced.py
rulelift/metrics/basic.py
rulelift/metrics/stability.py
rulelift/mining/__init__.py
rulelift/mining/decision_tree.py
rulelift/mining/multi_feature.py
rulelift/mining/single_feature.py
rulelift/mining/tree_rule_extractor.py
rulelift/mining/xgboost_rule_miner.py
rulelift/utils/__init__.py
rulelift/utils/data_loader.py
rulelift/utils/data_processing.py
rulelift/utils/validation.py
rulelift/visualization/__init__.py
rulelift/visualization/rule.py
rulelift-1.3.0.dist-info/licenses/LICENSE
rulelift-1.3.0.dist-info/METADATA
rulelift-1.3.0.dist-info/WHEEL
rulelift-1.3.0.dist-info/top_level.txt
rulelift-1.3.0.dist-info/RECORD
