Metadata-Version: 2.4
Name: rulelift
Version: 1.3.0
Summary: A tool for analyzing rule effectiveness in credit risk management
Home-page: https://github.com/aialgorithm/rulelift
Author: aialgorithm
Author-email: aialgorithm@example.com
Classifier: Programming Language :: Python :: 3
Classifier: License :: OSI Approved :: MIT License
Classifier: Operating System :: OS Independent
Classifier: Intended Audience :: Financial and Insurance Industry
Classifier: Topic :: Scientific/Engineering :: Information Analysis
Classifier: Topic :: Software Development :: Libraries :: Python Modules
Requires-Python: >=3.6
License-File: LICENSE
Requires-Dist: pandas<2.4.0,>=1.0.0
Requires-Dist: numpy<2.5.0,>=1.18.0
Requires-Dist: scikit-learn<1.9.0,>=0.24.0
Requires-Dist: matplotlib<3.11.0,>=3.3.0
Requires-Dist: seaborn<0.14.0,>=0.11.0
Requires-Dist: openpyxl>=3.0.0
Provides-Extra: visualization
Requires-Dist: networkx<3.7.0,>=2.5.0; extra == "visualization"
Requires-Dist: graphviz<1.0.0,>=0.16; extra == "visualization"
Provides-Extra: all
Requires-Dist: networkx<3.7.0,>=2.5.0; extra == "all"
Requires-Dist: graphviz<1.0.0,>=0.16; extra == "all"
Dynamic: author
Dynamic: author-email
Dynamic: classifier
Dynamic: description
Dynamic: description-content-type
Dynamic: home-page
Dynamic: license-file
Dynamic: provides-extra
Dynamic: requires-dist
Dynamic: requires-python
Dynamic: summary
